{
        "Language": "en",
        "PreKey": "Raza",
        "AutoUpdate": false,
        "MainColor": "#9900FF",
        "MainName": "[ FCA-HZI ]",
        "Uptime": true,
        "Config": "default",
        "DevMode": true,
        "Login2Fa": false,
        "AutoLogin": false,
        "BroadCast": true,
        "AuthString": "",
        "EncryptFeature": false,
        "ResetDataLogin": false,
        "AutoInstallNode": true,
        "AntiSendAppState": true,
        "AutoRestartMinutes": 0,
        "RestartMQTT_Minutes": 60,
        "Websocket_Extension": {
                "Status": true,
                "ResetData": false,
                "AppState_Path": "appstate.json"[
    {
        "key": "dbln",
        "value": "%7B%2261586201410496%22%3A%22unHRIYtL%22%7D",
        "domain": "facebook.com",
        "path": "/login/device-based/",
        "hostOnly": false,
        "creation": "2026-03-13T12:39:14.351Z",
        "lastAccessed": "2026-03-13T12:39:14.351Z"
    },
    {
        "key": "datr",
        "value": "38uyacthK7kKLZVgrzNR6SNQ",
        "domain": "facebook.com",
        "path": "/",
        "hostOnly": false,
        "creation": "2026-03-13T12:39:14.351Z",
        "lastAccessed": "2026-03-13T12:39:14.351Z"
    },
    {
        "key": "sb",
        "value": "38uyac_XzLqoN_A4gVirG0ah",
        "domain": "facebook.com",
        "path": "/",
        "hostOnly": false,
        "creation": "2026-03-13T12:39:14.351Z",
        "lastAccessed": "2026-03-13T12:39:14.351Z"
    },
    {
        "key": "ps_l",
        "value": "1",
        "domain": "facebook.com",
        "path": "/",
        "hostOnly": false,
        "creation": "2026-03-13T12:39:14.351Z",
        "lastAccessed": "2026-03-13T12:39:14.351Z"
    },
    {
        "key": "ps_n",
        "value": "1",
        "domain": "facebook.com",
        "path": "/",
        "hostOnly": false,
        "creation": "2026-03-13T12:39:14.351Z",
        "lastAccessed": "2026-03-13T12:39:14.351Z"
    },
    {
        "key": "c_user",
        "value": "61586201410496",
        "domain": "facebook.com",
        "path": "/",
        "hostOnly": false,
        "creation": "2026-03-13T12:39:14.351Z",
        "lastAccessed": "2026-03-13T12:39:14.351Z"
    },
    {
        "key": "xs",
        "value": "12%3AhT1yiiwpuRIpjQ%3A2%3A1773401925%3A-1%3A-1",
        "domain": "facebook.com",
        "path": "/",
        "hostOnly": false,
        "creation": "2026-03-13T12:39:14.351Z",
        "lastAccessed": "2026-03-13T12:39:14.351Z"
    },
    {
        "key": "fr",
        "value": "07etUn13PCeXo7qYN.AWeULeygV0TA8ujzrU7BMSUYWZUWQmSWa6mtxrQXLh04y5LtqSQ.Bpssvf..AAA.0.0.Bps_dM.AWeV0SMrLF0nhQ69OjHxFzQMj94",
        "domain": "facebook.com",
        "path": "/",
        "hostOnly": false,
        "creation": "2026-03-13T12:39:14.352Z",
        "lastAccessed": "2026-03-13T12:39:14.352Z"
    },
    {
        "key": "locale",
        "value": "en_GB",
        "domain": "facebook.com",
        "path": "/",
        "hostOnly": false,
        "creation": "2026-03-13T12:39:14.352Z",
        "lastAccessed": "2026-03-13T12:39:14.352Z"
    },
    {
        "key": "pas",
        "value": "100081123094513%3AoVi4HJpzEy%2C61586201410496%3ANUh4lG1A7Q",
        "domain": "facebook.com",
        "path": "/",
        "hostOnly": false,
        "creation": "2026-03-13T12:39:14.352Z",
        "lastAccessed": "2026-03-13T12:39:14.352Z"
    },
    {
        "key": "wl_cbv",
        "value": "v2%3Bclient_version%3A3110%3Btimestamp%3A1773401933",
        "domain": "facebook.com",
        "path": "/",
        "hostOnly": false,
        "creation": "2026-03-13T12:39:14.352Z",
        "lastAccessed": "2026-03-13T12:39:14.352Z"
    },
    {
        "key": "fbl_st",
        "value": "101431303%3BT%3A29556698",
        "domain": "facebook.com",
        "path": "/",
        "hostOnly": false,
        "creation": "2026-03-13T12:39:14.352Z",
        "lastAccessed": "2026-03-13T12:39:14.352Z"
    },
    {
        "key": "vpd",
        "value": "v1%3B676x360x2",
        "domain": "facebook.com",
        "path": "/",
        "hostOnly": false,
        "creation": "2026-03-13T12:39:14.352Z",
        "lastAccessed": "2026-03-13T12:39:14.352Z"
    }
]
        },
        "HTML": {
                "HTML": false,
                "UserName": "Aadil Khan",
                "MusicLink": "https://files.catbox.moe/h6dtdh.mp3"
        },
        "AntiGetInfo": {
                "Database_Type": "default",
                "AntiGetThreadInfo": false,
                "AntiGetUserInfo": false
        },
        "Stable_Version": {
                "Accept": false,
                "Version": ""
        },
        "CheckPointBypass": {
                "956": {
                        "Allow": false,
                        "Difficult": "Easy",
                        "Notification": "Turn on with AutoLogin!"
                }
        },
        "AntiStuckAndMemoryLeak": {
                "AutoRestart": {
                        "Use": false,
                        "Explain": "When this feature is turned on, the system will continuously check and confirm that if memory usage reaches 90%, it will automatically restart to avoid freezing or stopping."
                },
                "LogFile": {
                        "Use": false,
                        "Explain": "Record memory usage logs to fix errors. Default location: Raza_DataBase/memory.logs"
                }
        }
}
